LICENSE.txt
MANIFEST.in
README.md
release_notes.md
setup.py
frozenordereddict/VERSION.txt
frozenordereddict/__init__.py
frozenordereddict.egg-info/PKG-INFO
frozenordereddict.egg-info/SOURCES.txt
frozenordereddict.egg-info/dependency_links.txt
frozenordereddict.egg-info/top_level.txt
tests/__init__.py
tests/test_frozenordereddict.py