Metadata-Version: 2.1
Name: frozenordereddict
Version: 1.3.1
Summary: Frozen OrderedDict.
Home-page: https://github.com/wsmith323/frozenordereddict
Author: Warren A. Smith
Author-email: warren@wandrsmith.net
License: MIT
Keywords: ordereddict frozendict frozenordereddict orderedfrozendict ordered frozen dict
Platform: UNKNOWN
Classifier: License :: OSI Approved :: MIT License
Classifier: Programming Language :: Python :: 2
Classifier: Programming Language :: Python :: 2.7
Classifier: Programming Language :: Python :: 3
